qiskit_scaleway/__init__.py
qiskit_scaleway/provider.py
qiskit_scaleway/versions.py
qiskit_scaleway/backends/__init__.py
qiskit_scaleway/backends/base_backend.py
qiskit_scaleway/backends/base_job.py
qiskit_scaleway/backends/aer/__init__.py
qiskit_scaleway/backends/aer/backend.py
qiskit_scaleway/backends/aqt/__init__.py
qiskit_scaleway/backends/aqt/backend.py
qiskit_scaleway/backends/iqm/__init__.py
qiskit_scaleway/backends/iqm/backend.py
qiskit_scaleway/backends/iqm/move_gate.py
qiskit_scaleway/backends/qsim/__init__.py
qiskit_scaleway/backends/qsim/backend.py
qiskit_scaleway/backends/qsim/job.py
qiskit_scaleway/primitives/__init__.py
qiskit_scaleway/primitives/estimator.py
qiskit_scaleway/primitives/sampler.py
qiskit_scaleway/utils/__init__.py
qiskit_scaleway/utils/target.py
qiskit_scaleway-0.3.6.dist-info/licenses/LICENSE
qiskit_scaleway-0.3.6.dist-info/METADATA
qiskit_scaleway-0.3.6.dist-info/WHEEL
qiskit_scaleway-0.3.6.dist-info/top_level.txt
qiskit_scaleway-0.3.6.dist-info/RECORD
