Metadata-Version: 2.4
Name: qiskit_scaleway
Version: 0.3.6
Summary: A Qiskit package to connect to Scaleway Quantum as a Service
Author: The Scaleway Developers
Author-email: vmacheret@scaleway.com
License: Apache 2
Project-URL: Documentation, https://www.scaleway.com/en/quantum-as-a-service/
Project-URL: Source, https://github.com/scaleway/qiskit-scaleway
Project-URL: Tracker, https://github.com/scaleway/qiskit-scaleway/issues
Requires-Python: >=3.12.0
License-File: LICENSE
Requires-Dist: qiskit~=2.1
Requires-Dist: qiskit-aer~=0.17
Requires-Dist: randomname>=0.2.1
Requires-Dist: dataclasses-json>=0.6.4
Requires-Dist: dataclasses>=0.6
Requires-Dist: scaleway-qaas-client>=0.1.23
Requires-Dist: qio>=0.1.17
Dynamic: author
Dynamic: author-email
Dynamic: description
Dynamic: description-content-type
Dynamic: license
Dynamic: license-file
Dynamic: project-url
Dynamic: requires-dist
Dynamic: requires-python
Dynamic: summary
